myvirtualenvwrapper/__init__.py
myvirtualenvwrapper-0.0.1.dist-info/LICENSE
myvirtualenvwrapper-0.0.1.dist-info/METADATA
myvirtualenvwrapper-0.0.1.dist-info/WHEEL
myvirtualenvwrapper-0.0.1.dist-info/top_level.txt
myvirtualenvwrapper-0.0.1.dist-info/RECORD
